Metadata-Version: 2.1
Name: tree-print
Version: 0.0.0
Summary: A CLI utility to print directory structure.
Author: Max Curzi
Author-email: massimiliano.curzi@gmail.com
License: MIT
Requires-Python: >=3.5
License-File: LICENSE
